<?xml version="1.0" encoding="UTF-8" ?>
<searchresults timestamp='Sat, 27 Feb 16 14:00:59 +0000' attribution='Data © OpenStreetMap contributors, ODbL 1.0. http://www.openstreetmap.org/copyright' querystring='mcdonalds warszawa' polygon='true' exclude_place_ids='23660567,90165617,23120552,20629075,45695893,41939230,103490440,25362513,127996921,48771711' more_url='http://nominatim.openstreetmap.org/search.php?format=xml&amp;exclude_place_ids=23660567,90165617,23120552,20629075,45695893,41939230,103490440,25362513,127996921,48771711&amp;polygon=1&amp;q=mcdonalds+warszawa'>
<place place_id='23660567' osm_type='node' osm_id='2440688102' place_rank='30' boundingbox="52.2254064,52.2255064,20.2659433,20.2660433" polygonpoints='[[20.2659933,52.2255064],[20.266028655339,52.225491755339],[20.2660433,52.2254564],[20.266028655339,52.225421044661],[20.2659933,52.2254064],[20.265957944661,52.225421044661],[20.2659433,52.2254564],[20.265957944661,52.225491755339]]' lat='52.2254564' lon='20.2659933' display_name='McDonald&#039;s, 2C, Wojtówka, gmina Sochaczew, powiat sochaczewski, mazowieckie, 96-500, Polska' class='amenity' type='fast_food' importance='0.62174456852176' icon='http://nominatim.openstreetmap.org/images/mapicons/food_fastfood.p.20.png'/><place place_id='90165617' osm_type='way' osm_id='134754664' place_rank='22' boundingbox="52.3317422,52.3324339,20.9652016,20.967053" polygonpoints='[["20.9652016","52.3322936"],["20.9653077","52.3323397"],["20.9655237","52.3324339"],["20.9658308","52.3321709"],["20.9659016","52.332112"],["20.9659397","52.3321278"],["20.9661555","52.3322148"],["20.9665756","52.3323932"],["20.967053","52.3319737"],["20.9666403","52.3318437"],["20.9665947","52.3318297"],["20.9665036","52.3318008"],["20.9663178","52.3317422"],["20.9657896","52.3317971"],["20.9652016","52.3322936"]]' lat='52.33204285' lon='20.9662364332708' display_name='McDonald&#039;s, 1/3, Białołęka, Warszawa, mazowieckie, 03-115, Polska' class='landuse' type='construction' importance='0.3'/><place place_id='23120552' osm_type='node' osm_id='2331589534' place_rank='30' boundingbox="52.2121603,52.2122603,20.9511673,20.9512673" polygonpoints='[[20.9512173,52.2122603],[20.951252655339,52.212245655339],[20.9512673,52.2122103],[20.951252655339,52.212174944661],[20.9512173,52.2121603],[20.951181944661,52.212174944661],[20.9511673,52.2122103],[20.951181944661,52.212245655339]]' lat='52.2122103' lon='20.9512173' display_name='McDonalds, 148, Aleje Jerozolimskie, Szczęśliwice, Ochota, Warszawa, mazowieckie, 02-204, Polska' class='amenity' type='fast_food' importance='0.201' icon='http://nominatim.openstreetmap.org/images/mapicons/food_fastfood.p.20.png'/><place place_id='20629075' osm_type='node' osm_id='2077293216' place_rank='30' boundingbox="52.3051323,52.3052323,21.0570364,21.0571364" polygonpoints='[[21.0570864,52.3052323],[21.057121755339,52.305217655339],[21.0571364,52.3051823],[21.057121755339,52.305146944661],[21.0570864,52.3051323],[21.057051044661,52.305146944661],[21.0570364,52.3051823],[21.057051044661,52.305217655339]]' lat='52.3051823' lon='21.0570864' display_name='McDonald&#039;s, 15, Głębocka, Bródno-Podgrodzie, Targówek, Warszawa, mazowieckie, Polska' class='amenity' type='fast_food' importance='0.101' icon='http://nominatim.openstreetmap.org/images/mapicons/food_fastfood.p.20.png'/><place place_id='45695893' osm_type='node' osm_id='3307931433' place_rank='30' boundingbox="52.1791643,52.1792643,21.0032241,21.0033241" polygonpoints='[[21.0032741,52.1792643],[21.003309455339,52.179249655339],[21.0033241,52.1792143],[21.003309455339,52.179178944661],[21.0032741,52.1791643],[21.003238744661,52.179178944661],[21.0032241,52.1792143],[21.003238744661,52.179249655339]]' lat='52.1792143' lon='21.0032741' display_name='McDonald&#039;s, 12, Wołoska, Zagościniec, Mokotów, Warszawa, mazowieckie, 02-675, Polska' class='amenity' type='fast_food' importance='0.101' icon='http://nominatim.openstreetmap.org/images/mapicons/food_fastfood.p.20.png'/><place place_id='41939230' osm_type='node' osm_id='3048224518' place_rank='30' boundingbox="52.2207141,52.2208141,20.9156457,20.9157457" polygonpoints='[[20.9156957,52.2208141],[20.915731055339,52.220799455339],[20.9157457,52.2207641],[20.915731055339,52.220728744661],[20.9156957,52.2207141],[20.915660344661,52.220728744661],[20.9156457,52.2207641],[20.915660344661,52.220799455339]]' lat='52.2207641' lon='20.9156957' display_name='McDonald&#039;s, Połczyńska, Osiedle Lazurowa, Bemowo, Warszawa, mazowieckie, 01-376, Polska' class='amenity' type='fast_food' importance='0.101' icon='http://nominatim.openstreetmap.org/images/mapicons/food_fastfood.p.20.png'/><place place_id='103490440' osm_type='way' osm_id='191892320' place_rank='30' boundingbox="52.3085172,52.3088046,20.9286683,20.9292361" polygonpoints='[["20.9286683","52.3086778"],["20.9287065","52.3087058"],["20.9287429","52.3086872"],["20.9289032","52.3088046"],["20.9292361","52.3086346"],["20.9290757","52.3085172"],["20.9287776","52.3086694"],["20.9287395","52.3086415"],["20.9286683","52.3086778"]]' lat='52.30865545' lon='20.9290000966815' display_name='McDonald&#039;s, 60, Pułkowa, Huta, Bielany, Warszawa, mazowieckie, 01-969, Polska' class='amenity' type='fast_food' importance='0.101' icon='http://nominatim.openstreetmap.org/images/mapicons/food_fastfood.p.20.png'/><place place_id='25362513' osm_type='node' osm_id='2567077054' place_rank='30' boundingbox="52.1687288,52.1688288,21.0835026,21.0836026" polygonpoints='[[21.0835526,52.1688288],[21.083587955339,52.168814155339],[21.0836026,52.1687788],[21.083587955339,52.168743444661],[21.0835526,52.1687288],[21.083517244661,52.168743444661],[21.0835026,52.1687788],[21.083517244661,52.168814155339]]' lat='52.1687788' lon='21.0835526' display_name='McDrive, 35, Wiertnicza, Wilanów Niski, Wilanów, Warszawa, mazowieckie, 02-952, Polska' class='amenity' type='fast_food' importance='0.101' icon='http://nominatim.openstreetmap.org/images/mapicons/food_fastfood.p.20.png'/><place place_id='127996921' osm_type='way' osm_id='288935488' place_rank='30' boundingbox="52.228678,52.2292485,21.0035437,21.004133" polygonpoints='[["21.0035437","52.2291847"],["21.0038405","52.2292485"],["21.004133","52.2287432"],["21.003835","52.228678"],["21.0037875","52.2287217"],["21.0036922","52.228806"],["21.0035655","52.2290247"],["21.0035501","52.2291253"],["21.0035437","52.2291847"]]' lat='52.22891535' lon='21.0038310992777' display_name='McDonald&#039;s, Galeria wschodnia, IV, Śródmieście, Warszawa, mazowieckie, 00-118, Polska' class='amenity' type='fast_food' importance='0.101' icon='http://nominatim.openstreetmap.org/images/mapicons/food_fastfood.p.20.png'/><place place_id='48771711' osm_type='node' osm_id='3660993621' place_rank='30' boundingbox="52.258066,52.258166,20.986422,20.986522" polygonpoints='[[20.986472,52.258166],[20.986507355339,52.258151355339],[20.986522,52.258116],[20.986507355339,52.258080644661],[20.986472,52.258066],[20.986436644661,52.258080644661],[20.986422,52.258116],[20.986436644661,52.258151355339]]' lat='52.258116' lon='20.986472' display_name='McDonald&#039;s, 82, Aleja Jana Pawła II, I, Śródmieście, Warszawa, mazowieckie, 01-065, Polska' class='amenity' type='fast_food' importance='0.101' icon='http://nominatim.openstreetmap.org/images/mapicons/food_fastfood.p.20.png'/></searchresults>